activitypub/__init__.py
activitypub/helper.py
activitypub/model.py
activitypub_py-0.1.2.dist-info/LICENSE
activitypub_py-0.1.2.dist-info/METADATA
activitypub_py-0.1.2.dist-info/WHEEL
activitypub_py-0.1.2.dist-info/RECORD
